MANIFEST.in
README.txt
setup.cfg
setup.py
docs/HISTORY.txt
docs/INSTALL.txt
docs/LICENSE.GPL
docs/LICENSE.txt
sc/__init__.py
sc.apyb.pythonbrasil6.egg-info/PKG-INFO
sc.apyb.pythonbrasil6.egg-info/SOURCES.txt
sc.apyb.pythonbrasil6.egg-info/dependency_links.txt
sc.apyb.pythonbrasil6.egg-info/entry_points.txt
sc.apyb.pythonbrasil6.egg-info/namespace_packages.txt
sc.apyb.pythonbrasil6.egg-info/not-zip-safe
sc.apyb.pythonbrasil6.egg-info/requires.txt
sc.apyb.pythonbrasil6.egg-info/top_level.txt
sc/apyb/__init__.py
sc/apyb/pythonbrasil6/README.txt
sc/apyb/pythonbrasil6/__init__.py
sc/apyb/pythonbrasil6/config.py
sc/apyb/pythonbrasil6/configure.zcml
sc/apyb/pythonbrasil6/dependencies.zcml
sc/apyb/pythonbrasil6/quickinstaller.py
sc/apyb/pythonbrasil6/setuphandlers.py
sc/apyb/pythonbrasil6/tests.py
sc/apyb/pythonbrasil6/version.txt
sc/apyb/pythonbrasil6/browser/__init__.py
sc/apyb/pythonbrasil6/browser/configure.zcml
sc/apyb/pythonbrasil6/browser/edicoes.py
sc/apyb/pythonbrasil6/docs/__init__.py
sc/apyb/pythonbrasil6/docs/browser.txt
sc/apyb/pythonbrasil6/locales/manual.pot
sc/apyb/pythonbrasil6/locales/rebuildAll.sh
sc/apyb/pythonbrasil6/locales/sc.apyb.pythonbrasil6.pot
sc/apyb/pythonbrasil6/locales/pt_BR/LC_MESSAGES/sc.apyb.pythonbrasil6.po
sc/apyb/pythonbrasil6/profiles/default/import_steps.xml
sc/apyb/pythonbrasil6/profiles/default/metadata.xml
sc/apyb/pythonbrasil6/profiles/default/properties.xml
sc/apyb/pythonbrasil6/profiles/default/propertiestool.xml
sc/apyb/pythonbrasil6/profiles/default/sc.apyb.pythonbrasil6.txt
sc/apyb/pythonbrasil6/profiles/to101/propertiestool.xml
sc/apyb/pythonbrasil6/profiles/to200/propertiestool.xml
sc/apyb/pythonbrasil6/upgrades/__init__.py
sc/apyb/pythonbrasil6/upgrades/configure.zcml
sc/apyb/pythonbrasil6/upgrades/to01.py
sc/apyb/pythonbrasil6/upgrades/to20.py