Metadata-Version: 1.0
Name: sc.apyb.pythonbrasil6
Version: 2.0.2
Summary: Site policy for PythonBrasil[7]
Home-page: http://www.simplesconsultoria.com.br/
Author: Simples Consultoria
Author-email: products@simplesconsultoria.com.br
License: GPL
Keywords: apyb plone pythonbrasil plone3
Platform: UNKNOWN
Classifier: Framework :: Plone
Classifier: Framework :: Zope2
Classifier: Framework :: Zope3
Classifier: Programming Language :: Python
Classifier: Topic :: Software Development :: Libraries :: Python Modules
